generalanalysis/__init__.py
generalanalysis/__version__.py
generalanalysis/async_client.py
generalanalysis/client.py
generalanalysis/exceptions.py
generalanalysis/py.typed
generalanalysis/core/__init__.py
generalanalysis/core/auth.py
generalanalysis/core/http_client.py
generalanalysis/resources/__init__.py
generalanalysis/resources/async_guard_configurations.py
generalanalysis/resources/async_guards.py
generalanalysis/resources/async_organizations.py
generalanalysis/resources/async_projects.py
generalanalysis/resources/guard_configurations.py
generalanalysis/resources/guards.py
generalanalysis/resources/organizations.py
generalanalysis/resources/projects.py
generalanalysis/types/__init__.py
generalanalysis/types/guard_configs.py
generalanalysis/types/guards.py
generalanalysis/types/workspaces.py
generalanalysis-1.0.1.dist-info/METADATA
generalanalysis-1.0.1.dist-info/WHEEL
generalanalysis-1.0.1.dist-info/licenses/LICENSE
generalanalysis-1.0.1.dist-info/RECORD
