Metadata-Version: 2.4
Name: generalanalysis
Version: 1.0.1
Summary: Python SDK for General Analysis Guardrails
Project-URL: Homepage, https://generalanalysis.com
Project-URL: Repository, https://github.com/General-Analysis/ga-sdk
Project-URL: Documentation, https://docs.generalanalysis.com/
Author-email: General Analysis <support@generalanalysis.com>
License: MIT
License-File: LICENSE
Keywords: ai,api,guardrails,llm,safety,sdk
Classifier: Development Status :: 3 - Alpha
Classifier: Intended Audience :: Developers
Classifier: License :: OSI Approved :: MIT License
Classifier: Programming Language :: Python :: 3
Classifier: Programming Language :: Python :: 3.8
Classifier: Programming Language :: Python :: 3.9
Classifier: Programming Language :: Python :: 3.10
Classifier: Programming Language :: Python :: 3.11
Classifier: Programming Language :: Python :: 3.12
Requires-Python: >=3.8
Requires-Dist: httpx>=0.20.0
Requires-Dist: pydantic>=2.0.0
Requires-Dist: requests>=2.25.0
Provides-Extra: dev
Requires-Dist: black>=23.0.0; extra == 'dev'
Requires-Dist: mypy>=1.0.0; extra == 'dev'
Requires-Dist: pytest-asyncio>=0.21.0; extra == 'dev'
Requires-Dist: pytest-cov>=4.0.0; extra == 'dev'
Requires-Dist: pytest>=7.0.0; extra == 'dev'
Requires-Dist: ruff>=0.1.0; extra == 'dev'
Requires-Dist: types-requests>=2.28.0; extra == 'dev'
